team_pal/__init__.py
team_pal/container.py
team_pal/agent/codex_cli.py
team_pal/agent/codex_cli_session.py
team_pal/agent/codex_stream.py
team_pal/application/__init__.py
team_pal/application/agent_session.py
team_pal/application/bootstrap.py
team_pal/application/execution_service.py
team_pal/application/project_context.py
team_pal/application/python_env.py
team_pal/application/session_manager.py
team_pal/application/subcommands.py
team_pal/bootstrap/phase1.py
team_pal/bootstrap/phase2.py
team_pal/channel/__init__.py
team_pal/channel/cli/dispatcher.py
team_pal/channel/cli/factory.py
team_pal/channel/cli/listener.py
team_pal/channel/slack/__init__.py
team_pal/channel/slack/client.py
team_pal/channel/slack/dispatcher.py
team_pal/channel/slack/factory.py
team_pal/channel/slack/listener.py
team_pal/cli/__init__.py
team_pal/cli/__main__.py
team_pal/cli/cli_main.py
team_pal/config/__init__.py
team_pal/config/loader.py
team_pal/domain/__init__.py
team_pal/domain/execution.py
team_pal/domain/instruction.py
team_pal/domain/session.py
team_pal/localization/__init__.py
team_pal/localization/detector.py
team_pal/localization/formatter.py
team_pal/localization/messages.py
team_pal/logging/__init__.py
team_pal/logging/factory.py
team_pal/repository/session.py
team_pal/service/__init__.py
team_pal/service/execution.py
team_pal/service/facade.py
team_pal-0.3.0.dist-info/METADATA
team_pal-0.3.0.dist-info/WHEEL
team_pal-0.3.0.dist-info/entry_points.txt
team_pal-0.3.0.dist-info/top_level.txt
team_pal-0.3.0.dist-info/RECORD
