Metadata-Version: 2.4
Name: team-pal
Version: 0.3.0
Summary: Team Pal CLI entrypoint
Requires-Python: >=3.10
Requires-Dist: pexpect>=4.9.0
Requires-Dist: pytest>=8.4.2
Requires-Dist: python-dotenv>=1.1.1
Requires-Dist: slack-sdk>=3.37.0
